karney/__init__.py
karney/_common.py
karney/geodesic.py
karney/license.py
karney/util.py
karney-1.0.10.dist-info/LICENSE
karney-1.0.10.dist-info/METADATA
karney-1.0.10.dist-info/WHEEL
karney-1.0.10.dist-info/RECORD
