Metadata-Version: 2.1
Name: karney
Version: 1.0.10
Summary: Solves the direct and inverse geodesic problem.
License: MIT
Author: Per A. Brodtkorb
Requires-Python: >=3.8.0
Classifier: License :: OSI Approved :: MIT License
Classifier: Programming Language :: Python :: 3
Classifier: Programming Language :: Python :: 3.8
Classifier: Programming Language :: Python :: 3.9
Classifier: Programming Language :: Python :: 3.10
Classifier: Programming Language :: Python :: 3.11
Classifier: Programming Language :: Python :: 3.12
Requires-Dist: numpy (>=1.19) ; python_version >= "3.8"
Requires-Dist: numpy (>=1.25) ; python_version >= "3.12"
